mediaio/__init__.py
mediaio/config.py
mediaio/environment_vars.py
mediaio/mediaiorestclient.py
mediaio/resource.py
mediaio/task.py
mediaio/utils.py
mediaio/exceptions/__init__.py
mediaio/exceptions/exceptions.py
Online_UniConverter_python-2.0.0.0.dist-info/LICENCE
Online_UniConverter_python-2.0.0.0.dist-info/METADATA
Online_UniConverter_python-2.0.0.0.dist-info/WHEEL
Online_UniConverter_python-2.0.0.0.dist-info/top_level.txt
Online_UniConverter_python-2.0.0.0.dist-info/RECORD
