Metadata-Version: 2.1
Name: Online-UniConverter-python
Version: 2.0.0.0
Summary: Python REST API wrapper for media.io
Home-page: https://github.com/Online-UniConverter/Online-UniConverter-python
Author: wucm
Author-email: wucm@300624.cn
License: UNKNOWN
Platform: UNKNOWN
Classifier: Programming Language :: Python :: 3
Classifier: License :: OSI Approved :: MIT License
Classifier: Operating System :: OS Independent
Requires-Python: >=3
Requires-Dist: urllib3
Requires-Dist: requests
Requires-Dist: requests-toolbelt
